sglang_router/__init__.py
sglang_router/__main__.py
sglang_router/cli.py
sglang_router/launch_router.py
sglang_router/launch_server.py
sglang_router/mini_lb.py
sglang_router/router.py
sglang_router/router_args.py
sglang_router/sglang_router_rs.abi3.so
sglang_router/version.py
sglang_router-0.3.2.dist-info/METADATA
sglang_router-0.3.2.dist-info/WHEEL
sglang_router-0.3.2.dist-info/entry_points.txt
sglang_router.libs/libgcc_s-6d2d9dc8.so.1
sglang_router.libs/libstdc++-0c867d0f.so.6
sglang_router-0.3.2.dist-info/RECORD
