Metadata-Version: 2.4
Name: sglang-router
Version: 0.3.2
Classifier: Programming Language :: Python :: Implementation :: CPython
Classifier: Programming Language :: Rust
Classifier: Programming Language :: Python :: 3
Classifier: Programming Language :: Python :: 3.8
Classifier: Programming Language :: Python :: 3.9
Classifier: Programming Language :: Python :: 3.10
Classifier: Programming Language :: Python :: 3.11
Classifier: Programming Language :: Python :: 3.12
Classifier: Programming Language :: Python :: 3.13
Classifier: Programming Language :: Python :: 3.14
Requires-Dist: setproctitle
Requires-Dist: aiohttp
Requires-Dist: orjson
Requires-Dist: uvicorn
Requires-Dist: fastapi
Requires-Dist: requests>=2.25.0 ; extra == 'dev'
Requires-Dist: pytest>=7.0.0 ; extra == 'dev'
Provides-Extra: dev
Summary: High-performance Rust-based load balancer for SGLang with multiple routing algorithms and prefill-decode disaggregation support
Author-email: Simo Lin <linsimo.mark@gmail.com>, Chang Su <mckvtl@gmail.com>, Keyang Ru <rukeyang@gmail.com>, Byron Hsu <byronhsu1230@gmail.com>
License: Apache-2.0
Requires-Python: >=3.8
